{
  "address": "6mk5vkuRHtsUH97bqGKKLoqfj113SQwAThVLw5GyQDYx",
  "metadata": {
    "name": "covenant",
    "version": "0.1.0",
    "spec": "0.1.0"
  },
  "instructions": [
    {
      "name": "commit_to_proposal",
      "discriminator": [
        80,
        169,
        155,
        119,
        72,
        139,
        220,
        56
      ],
      "accounts": [
        {
          "name": "proposal",
          "writable": true,
          "pda": {
            "seeds": [
              {
                "kind": "const",
                "value": [
                  112,
                  114,
                  111,
                  112,
                  111,
                  115,
                  97,
                  108
                ]
              },
              {
                "kind": "arg",
                "path": "proposal_id"
              }
            ]
          }
        },
        {
          "name": "community",
          "pda": {
            "seeds": [
              {
                "kind": "const",
                "value": [
                  99,
                  111,
                  109,
                  109,
                  117,
                  110,
                  105,
                  116,
                  121
                ]
              },
              {
                "kind": "arg",
                "path": "community_id"
              }
            ]
          }
        },
        {
          "name": "member_state",
          "pda": {
            "seeds": [
              {
                "kind": "const",
                "value": [
                  109,
                  101,
                  109,
                  98,
                  101,
                  114
                ]
              },
              {
                "kind": "arg",
                "path": "community_id"
              },
              {
                "kind": "account",
                "path": "user"
              }
            ]
          }
        },
        {
          "name": "user_commitment",
          "writable": true,
          "pda": {
            "seeds": [
              {
                "kind": "const",
                "value": [
                  99,
                  111,
                  109,
                  109,
                  105,
                  116,
                  109,
                  101,
                  110,
                  116
                ]
              },
              {
                "kind": "arg",
                "path": "proposal_id"
              },
              {
                "kind": "account",
                "path": "user"
              }
            ]
          }
        },
        {
          "name": "user",
          "writable": true,
          "signer": true
        },
        {
          "name": "system_program",
          "address": "11111111111111111111111111111111"
        }
      ],
      "args": [
        {
          "name": "community_id",
          "type": "u64"
        },
        {
          "name": "proposal_id",
          "type": "u64"
        },
        {
          "name": "encrypted_commitment",
          "type": "bytes"
        },
        {
          "name": "commitment_nonce",
          "type": "u128"
        }
      ]
    },
    {
      "name": "create_community",
      "discriminator": [
        203,
        214,
        176,
        194,
        13,
        207,
        22,
        60
      ],
      "accounts": [
        {
          "name": "community",
          "writable": true,
          "pda": {
            "seeds": [
              {
                "kind": "const",
                "value": [
                  99,
                  111,
                  109,
                  109,
                  117,
                  110,
                  105,
                  116,
                  121
                ]
              },
              {
                "kind": "arg",
                "path": "community_id"
              }
            ]
          }
        },
        {
          "name": "admin_member",
          "writable": true,
          "pda": {
            "seeds": [
              {
                "kind": "const",
                "value": [
                  109,
                  101,
                  109,
                  98,
                  101,
                  114
                ]
              },
              {
                "kind": "arg",
                "path": "community_id"
              },
              {
                "kind": "account",
                "path": "admin"
              }
            ]
          }
        },
        {
          "name": "admin",
          "writable": true,
          "signer": true
        },
        {
          "name": "system_program",
          "address": "11111111111111111111111111111111"
        }
      ],
      "args": [
        {
          "name": "community_id",
          "type": "u64"
        },
        {
          "name": "name",
          "type": "string"
        },
        {
          "name": "description",
          "type": "string"
        },
        {
          "name": "voting_requirement",
          "type": {
            "defined": {
              "name": "VotingRequirement"
            }
          }
        }
      ]
    },
    {
      "name": "create_proposal",
      "discriminator": [
        132,
        116,
        68,
        174,
        216,
        160,
        198,
        22
      ],
      "accounts": [
        {
          "name": "proposal",
          "writable": true,
          "pda": {
            "seeds": [
              {
                "kind": "const",
                "value": [
                  112,
                  114,
                  111,
                  112,
                  111,
                  115,
                  97,
                  108
                ]
              },
              {
                "kind": "arg",
                "path": "proposal_id"
              }
            ]
          }
        },
        {
          "name": "community",
          "writable": true,
          "pda": {
            "seeds": [
              {
                "kind": "const",
                "value": [
                  99,
                  111,
                  109,
                  109,
                  117,
                  110,
                  105,
                  116,
                  121
                ]
              },
              {
                "kind": "arg",
                "path": "community_id"
              }
            ]
          }
        },
        {
          "name": "member_state",
          "pda": {
            "seeds": [
              {
                "kind": "const",
                "value": [
                  109,
                  101,
                  109,
                  98,
                  101,
                  114
                ]
              },
              {
                "kind": "arg",
                "path": "community_id"
              },
              {
                "kind": "account",
                "path": "creator"
              }
            ]
          }
        },
        {
          "name": "creator",
          "writable": true,
          "signer": true
        },
        {
          "name": "system_program",
          "address": "11111111111111111111111111111111"
        }
      ],
      "args": [
        {
          "name": "community_id",
          "type": "u64"
        },
        {
          "name": "proposal_id",
          "type": "u64"
        },
        {
          "name": "title",
          "type": "string"
        },
        {
          "name": "description",
          "type": "string"
        },
        {
          "name": "option_a",
          "type": "string"
        },
        {
          "name": "option_b",
          "type": "string"
        },
        {
          "name": "voting_end",
          "type": "i64"
        }
      ]
    },
    {
      "name": "execute_commitments",
      "discriminator": [
        132,
        88,
        118,
        223,
        190,
        15,
        56,
        62
      ],
      "accounts": [
        {
          "name": "proposal",
          "writable": true,
          "pda": {
            "seeds": [
              {
                "kind": "const",
                "value": [
                  112,
                  114,
                  111,
                  112,
                  111,
                  115,
                  97,
                  108
                ]
              },
              {
                "kind": "arg",
                "path": "proposal_id"
              }
            ]
          }
        },
        {
          "name": "authority",
          "writable": true,
          "signer": true
        }
      ],
      "args": [
        {
          "name": "proposal_id",
          "type": "u64"
        },
        {
          "name": "result_a",
          "type": "u64"
        },
        {
          "name": "result_b",
          "type": "u64"
        },
        {
          "name": "tally_nonce",
          "type": "u128"
        },
        {
          "name": "zk_proof",
          "type": "bytes"
        }
      ]
    },
    {
      "name": "finalize_proposal",
      "discriminator": [
        23,
        68,
        51,
        167,
        109,
        173,
        187,
        164
      ],
      "accounts": [
        {
          "name": "proposal",
          "writable": true,
          "pda": {
            "seeds": [
              {
                "kind": "const",
                "value": [
                  112,
                  114,
                  111,
                  112,
                  111,
                  115,
                  97,
                  108
                ]
              },
              {
                "kind": "arg",
                "path": "proposal_id"
              }
            ]
          }
        },
        {
          "name": "authority",
          "signer": true
        }
      ],
      "args": [
        {
          "name": "proposal_id",
          "type": "u64"
        }
      ]
    },
    {
      "name": "init_get_winning_option_comp_def",
      "discriminator": [
        64,
        9,
        220,
        6,
        118,
        109,
        113,
        253
      ],
      "accounts": [
        {
          "name": "payer",
          "writable": true,
          "signer": true
        },
        {
          "name": "mxe_account",
          "writable": true
        },
        {
          "name": "comp_def_account",
          "writable": true
        },
        {
          "name": "address_lookup_table",
          "writable": true
        },
        {
          "name": "lut_program",
          "address": "AddressLookupTab1e1111111111111111111111111"
        },
        {
          "name": "arcium_program",
          "address": "Arcj82pX7HxYKLR92qvgZUAd7vGS1k4hQvAFcPATFdEQ"
        },
        {
          "name": "system_program",
          "address": "11111111111111111111111111111111"
        }
      ],
      "args": []
    },
    {
      "name": "init_reveal_tally_comp_def",
      "discriminator": [
        107,
        78,
        64,
        206,
        75,
        159,
        140,
        88
      ],
      "accounts": [
        {
          "name": "payer",
          "writable": true,
          "signer": true
        },
        {
          "name": "mxe_account",
          "writable": true
        },
        {
          "name": "comp_def_account",
          "writable": true
        },
        {
          "name": "address_lookup_table",
          "writable": true
        },
        {
          "name": "lut_program",
          "address": "AddressLookupTab1e1111111111111111111111111"
        },
        {
          "name": "arcium_program",
          "address": "Arcj82pX7HxYKLR92qvgZUAd7vGS1k4hQvAFcPATFdEQ"
        },
        {
          "name": "system_program",
          "address": "11111111111111111111111111111111"
        }
      ],
      "args": []
    },
    {
      "name": "init_tally_vote_comp_def",
      "discriminator": [
        215,
        112,
        176,
        68,
        223,
        167,
        185,
        21
      ],
      "accounts": [
        {
          "name": "payer",
          "writable": true,
          "signer": true
        },
        {
          "name": "mxe_account",
          "writable": true
        },
        {
          "name": "comp_def_account",
          "writable": true
        },
        {
          "name": "address_lookup_table",
          "writable": true
        },
        {
          "name": "lut_program",
          "address": "AddressLookupTab1e1111111111111111111111111"
        },
        {
          "name": "arcium_program",
          "address": "Arcj82pX7HxYKLR92qvgZUAd7vGS1k4hQvAFcPATFdEQ"
        },
        {
          "name": "system_program",
          "address": "11111111111111111111111111111111"
        }
      ],
      "args": []
    },
    {
      "name": "join_community",
      "discriminator": [
        252,
        106,
        147,
        30,
        134,
        74,
        28,
        232
      ],
      "accounts": [
        {
          "name": "community",
          "writable": true,
          "pda": {
            "seeds": [
              {
                "kind": "const",
                "value": [
                  99,
                  111,
                  109,
                  109,
                  117,
                  110,
                  105,
                  116,
                  121
                ]
              },
              {
                "kind": "arg",
                "path": "community_id"
              }
            ]
          }
        },
        {
          "name": "member_state",
          "writable": true,
          "pda": {
            "seeds": [
              {
                "kind": "const",
                "value": [
                  109,
                  101,
                  109,
                  98,
                  101,
                  114
                ]
              },
              {
                "kind": "arg",
                "path": "community_id"
              },
              {
                "kind": "account",
                "path": "user"
              }
            ]
          }
        },
        {
          "name": "user",
          "writable": true,
          "signer": true
        },
        {
          "name": "system_program",
          "address": "11111111111111111111111111111111"
        }
      ],
      "args": [
        {
          "name": "community_id",
          "type": "u64"
        }
      ]
    },
    {
      "name": "leave_community",
      "discriminator": [
        218,
        140,
        41,
        66,
        8,
        140,
        33,
        161
      ],
      "accounts": [
        {
          "name": "community",
          "writable": true,
          "pda": {
            "seeds": [
              {
                "kind": "const",
                "value": [
                  99,
                  111,
                  109,
                  109,
                  117,
                  110,
                  105,
                  116,
                  121
                ]
              },
              {
                "kind": "arg",
                "path": "community_id"
              }
            ]
          }
        },
        {
          "name": "member_state",
          "writable": true,
          "pda": {
            "seeds": [
              {
                "kind": "const",
                "value": [
                  109,
                  101,
                  109,
                  98,
                  101,
                  114
                ]
              },
              {
                "kind": "arg",
                "path": "community_id"
              },
              {
                "kind": "account",
                "path": "user"
              }
            ]
          }
        },
        {
          "name": "user",
          "writable": true,
          "signer": true
        }
      ],
      "args": [
        {
          "name": "community_id",
          "type": "u64"
        }
      ]
    },
    {
      "name": "voting_closes",
      "discriminator": [
        118,
        185,
        221,
        82,
        95,
        81,
        61,
        26
      ],
      "accounts": [
        {
          "name": "proposal",
          "writable": true,
          "pda": {
            "seeds": [
              {
                "kind": "const",
                "value": [
                  112,
                  114,
                  111,
                  112,
                  111,
                  115,
                  97,
                  108
                ]
              },
              {
                "kind": "arg",
                "path": "proposal_id"
              }
            ]
          }
        },
        {
          "name": "clock",
          "address": "SysvarC1ock11111111111111111111111111111111"
        }
      ],
      "args": [
        {
          "name": "proposal_id",
          "type": "u64"
        }
      ]
    }
  ],
  "accounts": [
    {
      "name": "CommunityState",
      "discriminator": [
        133,
        66,
        57,
        235,
        219,
        148,
        104,
        230
      ]
    },
    {
      "name": "MXEAccount",
      "discriminator": [
        103,
        26,
        85,
        250,
        179,
        159,
        17,
        117
      ]
    },
    {
      "name": "MemberState",
      "discriminator": [
        41,
        28,
        21,
        90,
        91,
        49,
        228,
        104
      ]
    },
    {
      "name": "ProposalState",
      "discriminator": [
        251,
        209,
        129,
        206,
        222,
        199,
        248,
        29
      ]
    },
    {
      "name": "UserCommitment",
      "discriminator": [
        163,
        79,
        14,
        230,
        58,
        105,
        84,
        24
      ]
    }
  ],
  "events": [
    {
      "name": "ProposalFinalized",
      "discriminator": [
        159,
        104,
        210,
        220,
        86,
        209,
        61,
        51
      ]
    }
  ],
  "errors": [
    {
      "code": 6000,
      "name": "VotingNotStarted",
      "msg": "voting window has not opened yet"
    },
    {
      "code": 6001,
      "name": "VotingClosed",
      "msg": "voting window is closed"
    },
    {
      "code": 6002,
      "name": "VotingStillActive",
      "msg": "voting is still active"
    },
    {
      "code": 6003,
      "name": "TallyNotStarted",
      "msg": "tally has not been triggered"
    },
    {
      "code": 6004,
      "name": "AlreadyFinalized",
      "msg": "proposal already finalized"
    },
    {
      "code": 6005,
      "name": "Unauthorized",
      "msg": "not authorized"
    },
    {
      "code": 6006,
      "name": "InvalidProof",
      "msg": "invalid zk proof"
    },
    {
      "code": 6007,
      "name": "AlreadyMember",
      "msg": "already a member of this community"
    },
    {
      "code": 6008,
      "name": "AdminCannotLeave",
      "msg": "admin cannot leave the community"
    },
    {
      "code": 6009,
      "name": "WrongCommunity",
      "msg": "proposal does not belong to this community"
    },
    {
      "code": 6010,
      "name": "TokenAccountRequired",
      "msg": "token account is required for this community"
    },
    {
      "code": 6011,
      "name": "WrongTokenMint",
      "msg": "token account has wrong mint"
    },
    {
      "code": 6012,
      "name": "WrongTokenOwner",
      "msg": "token account has wrong owner"
    },
    {
      "code": 6013,
      "name": "InsufficientTokenBalance",
      "msg": "insufficient token balance to vote"
    },
    {
      "code": 6014,
      "name": "InvalidTokenAccount",
      "msg": "invalid token account data"
    }
  ],
  "types": [
    {
      "name": "CommunityState",
      "type": {
        "kind": "struct",
        "fields": [
          {
            "name": "community_id",
            "type": "u64"
          },
          {
            "name": "admin",
            "type": "pubkey"
          },
          {
            "name": "name",
            "type": "string"
          },
          {
            "name": "description",
            "type": "string"
          },
          {
            "name": "voting_requirement",
            "type": {
              "defined": {
                "name": "VotingRequirement"
              }
            }
          },
          {
            "name": "member_count",
            "type": "u64"
          },
          {
            "name": "proposal_count",
            "type": "u64"
          },
          {
            "name": "created_at",
            "type": "i64"
          },
          {
            "name": "bump",
            "type": "u8"
          }
        ]
      }
    },
    {
      "name": "MXEAccount",
      "docs": [
        "A MPC Execution Environment."
      ],
      "type": {
        "kind": "struct",
        "fields": [
          {
            "name": "cluster",
            "type": {
              "option": "u32"
            }
          },
          {
            "name": "keygen_offset",
            "type": "u64"
          },
          {
            "name": "key_recovery_init_offset",
            "type": "u64"
          },
          {
            "name": "mxe_program_id",
            "type": "pubkey"
          },
          {
            "name": "authority",
            "type": {
              "option": "pubkey"
            }
          },
          {
            "name": "utility_pubkeys",
            "type": {
              "defined": {
                "name": "SetUnset",
                "generics": [
                  {
                    "kind": "type",
                    "type": {
                      "defined": {
                        "name": "UtilityPubkeys"
                      }
                    }
                  }
                ]
              }
            }
          },
          {
            "name": "lut_offset_slot",
            "type": "u64"
          },
          {
            "name": "computation_definitions",
            "type": {
              "vec": "u32"
            }
          },
          {
            "name": "status",
            "type": {
              "defined": {
                "name": "MxeStatus"
              }
            }
          },
          {
            "name": "bump",
            "type": "u8"
          }
        ]
      }
    },
    {
      "name": "MemberState",
      "type": {
        "kind": "struct",
        "fields": [
          {
            "name": "community_id",
            "type": "u64"
          },
          {
            "name": "member",
            "type": "pubkey"
          },
          {
            "name": "joined_at",
            "type": "i64"
          },
          {
            "name": "bump",
            "type": "u8"
          }
        ]
      }
    },
    {
      "name": "MxeStatus",
      "docs": [
        "The status of an MXE."
      ],
      "type": {
        "kind": "enum",
        "variants": [
          {
            "name": "Active"
          },
          {
            "name": "Migration"
          }
        ]
      }
    },
    {
      "name": "ProposalFinalized",
      "type": {
        "kind": "struct",
        "fields": [
          {
            "name": "proposal_id",
            "type": "u64"
          },
          {
            "name": "result_a",
            "type": "u64"
          },
          {
            "name": "result_b",
            "type": "u64"
          },
          {
            "name": "winner",
            "type": "u8"
          }
        ]
      }
    },
    {
      "name": "ProposalState",
      "type": {
        "kind": "struct",
        "fields": [
          {
            "name": "community_id",
            "type": "u64"
          },
          {
            "name": "proposal_id",
            "type": "u64"
          },
          {
            "name": "creator",
            "type": "pubkey"
          },
          {
            "name": "title",
            "type": "string"
          },
          {
            "name": "description",
            "type": "string"
          },
          {
            "name": "option_a",
            "type": "string"
          },
          {
            "name": "option_b",
            "type": "string"
          },
          {
            "name": "voting_start",
            "type": "i64"
          },
          {
            "name": "voting_end",
            "type": "i64"
          },
          {
            "name": "status",
            "type": {
              "defined": {
                "name": "ProposalStatus"
              }
            }
          },
          {
            "name": "commitment_count",
            "type": "u64"
          },
          {
            "name": "tally_nonce",
            "type": "u128"
          },
          {
            "name": "result_option_a",
            "type": "u64"
          },
          {
            "name": "result_option_b",
            "type": "u64"
          },
          {
            "name": "zk_proof",
            "type": "bytes"
          },
          {
            "name": "bump",
            "type": "u8"
          }
        ]
      }
    },
    {
      "name": "ProposalStatus",
      "type": {
        "kind": "enum",
        "variants": [
          {
            "name": "Created"
          },
          {
            "name": "Voting"
          },
          {
            "name": "TallyStarted"
          },
          {
            "name": "Finalized"
          }
        ]
      }
    },
    {
      "name": "SetUnset",
      "docs": [
        "Utility struct to store a value that needs to be set by a certain number of participants (keys",
        "in our case). Once all participants have set the value, the value is considered set and we only",
        "store it once."
      ],
      "generics": [
        {
          "kind": "type",
          "name": "T"
        }
      ],
      "type": {
        "kind": "enum",
        "variants": [
          {
            "name": "Set",
            "fields": [
              {
                "generic": "T"
              }
            ]
          },
          {
            "name": "Unset",
            "fields": [
              {
                "generic": "T"
              },
              {
                "vec": "bool"
              }
            ]
          }
        ]
      }
    },
    {
      "name": "UserCommitment",
      "type": {
        "kind": "struct",
        "fields": [
          {
            "name": "proposal_id",
            "type": "u64"
          },
          {
            "name": "user",
            "type": "pubkey"
          },
          {
            "name": "encrypted_commitment",
            "type": "bytes"
          },
          {
            "name": "commitment_nonce",
            "type": "u128"
          },
          {
            "name": "timestamp",
            "type": "i64"
          },
          {
            "name": "bump",
            "type": "u8"
          }
        ]
      }
    },
    {
      "name": "UtilityPubkeys",
      "type": {
        "kind": "struct",
        "fields": [
          {
            "name": "x25519_pubkey",
            "type": {
              "array": [
                "u8",
                32
              ]
            }
          },
          {
            "name": "ed25519_verifying_key",
            "type": {
              "array": [
                "u8",
                32
              ]
            }
          },
          {
            "name": "elgamal_pubkey",
            "type": {
              "array": [
                "u8",
                32
              ]
            }
          },
          {
            "name": "pubkey_validity_proof",
            "type": {
              "array": [
                "u8",
                64
              ]
            }
          }
        ]
      }
    },
    {
      "name": "VotingRequirement",
      "type": {
        "kind": "enum",
        "variants": [
          {
            "name": "Open"
          },
          {
            "name": "TokenGated",
            "fields": [
              {
                "name": "mint",
                "type": "pubkey"
              },
              {
                "name": "min_amount",
                "type": "u64"
              }
            ]
          },
          {
            "name": "NftGated",
            "fields": [
              {
                "name": "collection_mint",
                "type": "pubkey"
              }
            ]
          }
        ]
      }
    }
  ]
}